Metadata-Version: 1.0
Name: compatify
Version: 0.0.1
Summary: A wrapper for making different version code compatible.
Home-page: UNKNOWN
Author: UNKNOWN
Author-email: UNKNOWN
License: UNKNOWN
Platform: UNKNOWN
